Workbook
Name Slicer_Company_ID: #N/A
Name Slicer_Year: #N/A

Sheet FINAL DASHBOARD
A1: KPI | B1: Formula | C1: Column1 | E1: Financial Performance, Forecasting & Budgeting Dashboard
A2: Total Revenue | B2: =SUM(Sheet1!D:D) -> 5.6094618e+08
A3: Total Profit | B3: =SUM(Sheet1!G:G) -> 1.0473882e+08
A4: Avg Profit Margin | B4: =AVERAGE(Sheet1!AH:AH) -> 0.16579803
A5: Avg Revenue Growth | B5: =AVERAGE(Sheet1!AJ:AJ) -> 0.021089248
D11: FORECAST MODEL | E11: Revenue | F11: Expenses | G11: Profit
D12: Current | E12: 464427.65 | F12: 422739.02 | G12: =(E12-F12) -> 41688.638 | R12: Quarter | S12: Revenue | T12: Expenses | U12: Profit
D13: Next Q1 | E13: =Sheet1!F11*(1+0.02086) -> 17568.856 | F13: =Sheet1!G11*(1+0.02039) -> 9570.4951 | G13: =(E13-F13) -> 7998.3613 | R13: Current | S13: 464427.65 | T13: 422739.02 | U13: =(S13-T13) -> 41688.638
D14: Next Q2 | E14: =Sheet1!F12*(1+0.02086) -> 24741.699 | F14: =Sheet1!G12*(1+0.02039) -> 16195.726 | G14: =(E14-F14) -> 8545.9734 | R14: Next Q1 | S14: =Sheet1!T12*(1+0.02086) -> 0.58016352 | T14: =Sheet1!U12*(1+0.02039) -> 0.095584796 | U14: =(S14-T14) -> 0.48457872
D15: Next Q3 | E15: =Sheet1!F13*(1+0.02086) -> 44948.784 | F15: =Sheet1!G13*(1+0.02039) -> 36837.78 | G15: =(E15-F15) -> 8111.0041 | R15: Next Q2 | S15: =Sheet1!T13*(1+0.02086) -> 0.90192371 | T15: =Sheet1!U13*(1+0.02039) -> 0.76296476 | U15: =(S15-T15) -> 0.13895895
D16: Next Q4 | E16: =Sheet1!F14*(1+0.02086) -> 27356.701 | F16: =Sheet1!G14*(1+0.02039) -> 14814.535 | G16: =(E16-F16) -> 12542.166 | R16: Next Q3 | S16: =Sheet1!T14*(1+0.02086) -> 0.36612815 | T16: =Sheet1!U14*(1+0.02039) -> 0.25934605 | U16: =(S16-T16) -> 0.10678211
H17: Column4 | I17: Forecast_Model sheet.2 | R17: Next Q4 | S17: =Sheet1!T15*(1+0.02086) -> 0.59094002 | T17: =Sheet1!U15*(1+0.02039) -> 0.44741461 | U17: =(S17-T17) -> 0.14352541
D18: BUDGET MODEL | E18: Revenue Growth | F18: Forecast Revenue | G18: FORECAST EXPENSE | H18: PROFIT | I18: Scenario2 | J18: Column7 | K18: Forecast_Model sheet.4
D19: Conservative | E19: 0.03 | F19: =214802*(1+0.03) -> 221246.06 | G19: =190523*(1+0.02039) -> 194407.76 | I19: Conservative
D20: Base | E20: 0.06 | F20: =214802*(1+0.06) -> 227690.12 | G20: =190523*(1+0.02039) -> 194407.76 | I20: Base
D21: Aggressive | E21: 0.09 | F21: =214802*(1+0.09) -> 234134.18 | G21: =190523*(1+0.02039) -> 194407.76 | I21: Aggressive

Sheet Sheet8
E1: GROWTH MOMENTUM
A3: Row Labels | B3: Count of QOQ
A4: 2015 | B4: 200
A5: 2016 | B5: 200
A6: 2017 | B6: 200
A7: 2018 | B7: 200
A8: 2019 | B8: 200
A9: 2020 | B9: 200
A10: 2021 | B10: 200
A11: 2022 | B11: 200
A12: 2023 | B12: 200
A13: 2024 | B13: 200
A14: (blank) | B14: 94
A15: Grand Total | B15: 2094

Sheet Sheet9
B1: MARGIN ANALYSIS
A3: Row Labels | B3: Count of OPERATING MARGIN | C3: Sum of NET MARGIN
A4: 2015 | B4: 200 | C4: 0.19365091
A5: 2016 | B5: 200 | C5: 0.18845342
A6: 2017 | B6: 200 | C6: 0.1837178
A7: 2018 | B7: 200 | C7: 0.18667815
A8: 2019 | B8: 200 | C8: 0.18569997
A9: 2020 | B9: 200 | C9: 0.18887677
A10: 2021 | B10: 200 | C10: 0.18284164
A11: 2022 | B11: 200 | C11: 0.18670455
A12: 2023 | B12: 200 | C12: 0.18364574
A13: 2024 | B13: 200 | C13: 0.19264829
A14: (blank) | B14: 84 | C14: #DIV/0!
A15: Grand Total | B15: #DIV/0! | C15: 0.18730172

Sheet Sheet10
B1: LEVERAGE ANALYSIS
A3: Row Labels | B3: Count of NET MARGIN
A4: 2015 | B4: 200
A5: 2016 | B5: 200
A6: 2017 | B6: 200
A7: 2018 | B7: 200
A8: 2019 | B8: 200
A9: 2020 | B9: 200
A10: 2021 | B10: 200
A11: 2022 | B11: 200
A12: 2023 | B12: 200
A13: 2024 | B13: 200
A14: (blank)
A15: Grand Total | B15: 2000

Sheet Sheet12
A3: Row Labels | B3: Sum of Net_Income
A4: 2015 | B4: 10884238 | H4: PROFIT TREND
A5: 2016 | B5: 10539789
A6: 2017 | B6: 10186260
A7: 2018 | B7: 10464308
A8: 2019 | B8: 10383191
A9: 2020 | B9: 10575243
A10: 2021 | B10: 10204184
A11: 2022 | B11: 10436274
A12: 2023 | B12: 10250882
A13: 2024 | B13: 10814451
A14: Grand Total | B14: 1.0473882e+08

Sheet Sheet13
F1: REVENUE BY COMPANY
A3: Row Labels | B3: Sum of Revenue
A4: CMP_001 | B4: 8959817.4
A5: CMP_002 | B5: 7153869.7
A6: CMP_003 | B6: 4257318.4
A7: CMP_004 | B7: 14849681
A8: CMP_005 | B8: 18998925
A9: CMP_006 | B9: 18776103
A10: CMP_007 | B10: 3170991.9
A11: CMP_008 | B11: 15177795
A12: CMP_009 | B12: 19790043
A13: CMP_010 | B13: 19901421
A14: CMP_011 | B14: 3635400.8
A15: CMP_012 | B15: 5040162.3
... A54: Grand Total | B54: 5.5919837e+08

Sheet Sheet5
D1: REVENUE TREND
A3: Row Labels | B3: Sum of Revenue
A4: 2015 | B4: 56205454
A5: 2016 | B5: 55927818
A6: 2017 | B6: 55445146
A7: 2018 | B7: 56055342
A8: 2019 | B8: 55913803
A9: 2020 | B9: 55990171
A10: 2021 | B10: 55808865
A11: 2022 | B11: 55897265
A12: 2023 | B12: 55818782
A13: 2024 | B13: 56135724
A14: Grand Total | B14: 5.5919837e+08

Sheet Sheet7
B1: PROFITABILITY ANALYSIS (Pivot) | E1: REVENUE VS EXPENSE
A3: Row Labels | B3: Sum of Revenue | C3: Sum of Expenses
A4: 2015 | B4: 56205454 | C4: 42807672
A5: 2016 | B5: 55927818 | C5: 42962112
A6: 2017 | B6: 55445146 | C6: 42813864
A7: 2018 | B7: 56055342 | C7: 43055154
A8: 2019 | B8: 55913803 | C8: 43012683
A9: 2020 | B9: 55990171 | C9: 42850525
A10: 2021 | B10: 55808865 | C10: 43008040
A11: 2022 | B11: 55897265 | C11: 42954005
A12: 2023 | B12: 55818782 | C12: 43011275
A13: 2024 | B13: 56135724 | C13: 42760079
A14: Grand Total | B14: 5.5919837e+08 | C14: 4.2923541e+08

Sheet Sheet11
F2: LEVERAGE ANALYSIS
A3: Row Labels | B3: Sum of Net_Income
A4: 2015 | B4: 10884238
A5: 2016 | B5: 10539789
A6: 2017 | B6: 10186260
A7: 2018 | B7: 10464308
A8: 2019 | B8: 10383191
A9: 2020 | B9: 10575243
A10: 2021 | B10: 10204184
A11: 2022 | B11: 10436274
A12: 2023 | B12: 10250882
A13: 2024 | B13: 10814451
A14: Grand Total | B14: 1.0473882e+08

Sheet Sheet1
A1: Year | B1: Quarter | C1: Company_ID | D1: Revenue | E1: Expenses | F1: Operating_Income | G1: Net_Income | H1: Assets | I1: Liabilities | J1: Equity | K1: Cash_Flow | L1: EPS | M1: ROE | N1: ROA | O1: Debt_to_Equity | P1: Stock_Price | Q1: Volume_Traded | R1: News_Sentiment_Score | S1: Social_Media_Buzz | T1: Sector_Trend_Index | U1: Global_Economic_Score | V1: Inflation_Rate | W1: Exchange_Rate | X1: Interest_Rate | Y1: Audit_Flag | Z1: Fraud_Flag | AA1: Market_Shock_Flag | AB1: Policy_Change_Flag | AC1: Target_Revenue_Next_Qtr | AD1: Target_Anomaly_Class | AE1: QOQ | AF1: YOY | AG1: OPERATING MARGIN | AH1: NET MARGIN | AI1: REVENUE VOLATILITY | AJ1: REVENUEGROWTH | AK1: EXPENSE GROWTH | AL1: AVG REVENUE GROWTH
A2: 2015 | B2: 1 | C2: CMP_001 | D2: 229991.31 | E2: 212058.66 | F2: 17932.651 | G2: 10592.371 | H2: 531737.38 | I2: 171875.3 | J2: 359862.07 | K2: 18585.013 | L2: 1.6524669 | M2: 2.943453 | N2: 1.9920305 | O2: 0.47761439 | P2: 359.87484 | Q2: 2685 | R2: -0.88717684 | S2: 343 | T2: 0.83244264 | U2: 0.21233911 | V2: 2.2727748 | W2: 64.585113 | X2: 4.4339379 | Y2: 0 | Z2: 0 | AA2: 0 | AB2: 0 | AC2: 232953.17 | AD2: 0 | AE2: =IF(C3=C2,(D3-D2)/D2,"") -> -0.066045037 | AF2: =IF(C6=C2,(D6-D2)/D2,"") -> -0.083335684 | AG2: =(D:D-E:E)/D:D -> 0.077970994 | AH2: =G2/D2 -> 0.046055528 | AI2: =_xlfn.STDEV.P(D:D)/AVERAGE(D:D) -> 0.56010785 | AJ2: =(D3-D2)/D2 -> -0.066045037 | AK2: =(E3-E2)/E2 -> -0.1015541 | AL2: =AVERAGE(AJ:AJ) -> 0.021089248
A3: 2015 | B3: 2 | C3: CMP_001 | D3: 214801.52 | E3: 190523.23 | F3: 24278.293 | G3: 7500.6536 | H3: 515383.51 | I3: 260626.23 | J3: 254757.28 | K3: 11386.872 | L3: 5.2894002 | M3: 2.9442353 | N3: 1.4553538 | O3: 1.0230374 | P3: 311.62153 | Q3: 31740 | R3: -0.099001496 | S3: 273 | T3: 0.94888554 | U3: 0.96563203 | V3: 6.6587814 | W3: 67.615344 | X3: 2.7813769 | Y3: 0 | Z3: 0 | AA3: 0 | AB3: 0 | AC3: 202861.82 | AD3: 0 | AE3: =IF(C4=C3,(D4-D3)/D3,"") -> 0.079610547 | AF3: =IF(C7=C3,(D7-D3)/D3,"") -> 0.059333302 | AG3: =(D:D-E:E)/D:D -> 0.11302663 | AH3: =G3/D3 -> 0.034918997 | AI3: =_xlfn.STDEV.P(D:D)/AVERAGE(D:D) -> 0.56010785 | AJ3: =(D4-D3)/D3 -> 0.079610547 | AK3: =(E4-E3)/E3 -> -0.026273487 | AL3: =AVERAGE(AJ:AJ) -> 0.021089248
A4: 2015 | B4: 3 | C4: CMP_001 | D4: 231901.99 | E4: 185517.52 | F4: 46384.469 | G4: 36708.803 | H4: 705013.59 | I4: 365679.35 | J4: 339334.24 | K4: 34481.62 | L4: 3.7741945 | M4: 10.817889 | N4: 5.2068221 | O4: 1.0776376 | P4: 392.06376 | Q4: 1161 | R4: -0.20969953 | S4: 995 | T4: 0.59789998 | U4: 0.92187424 | V4: 1.6194475 | W4: 64.899572 | X4: 2.3618183 | Y4: 0 | Z4: 0 | AA4: 0 | AB4: 0 | AC4: 226367.15 | AD4: 0 | AE4: =IF(C5=C4,(D5-D4)/D4,"") -> -0.08025127 | AF4: =IF(C8=C4,(D8-D4)/D4,"") -> -0.10234093 | AG4: =(D:D-E:E)/D:D -> 0.20001756 | AH4: =G4/D4 -> 0.15829447 | AI4: =_xlfn.STDEV.P(D:D)/AVERAGE(D:D) -> 0.56010785 | AJ4: =(D5-D4)/D4 -> -0.08025127 | AK4: =(E5-E4)/E4 -> 0.004707785 | AL4: =AVERAGE(AJ:AJ) -> 0.021089248
A5: 2015 | B5: 4 | C5: CMP_001 | D5: 213291.56 | E5: 186390.9 | F5: 26900.664 | G5: 9867.709 | H5: 458385.16 | I5: 318465.28 | J5: 139919.88 | K5: 16451.381 | L5: 3.5387905 | M5: 7.0523994 | N5: 2.1527113 | O5: 2.2760545 | P5: 22.650616 | Q5: 6258 | R5: -0.60231519 | S5: 391 | T5: 0.72900717 | U5: 0.77127035 | V5: 1.5183126 | W5: 68.961643 | X5: 2.9269525 | Y5: 0 | Z5: 0 | AA5: 0 | AB5: 0 | AC5: 220837.21 | AD5: 0 | AE5: =IF(C6=C5,(D6-D5)/D5,"") -> -0.011565089 | AF5: =IF(C9=C5,(D9-D5)/D5,"") -> 0.040801757 | AG5: =(D:D-E:E)/D:D -> 0.12612156 | AH5: =G5/D5 -> 0.046263945 | AI5: =_xlfn.STDEV.P(D:D)/AVERAGE(D:D) -> 0.56010785 | AJ5: =(D6-D5)/D5 -> -0.011565089 | AK5: =(E6-E5)/E5 -> -0.0034071718 | AL5: =AVERAGE(AJ:AJ) -> 0.021089248
A6: 2016 | B6: 1 | C6: CMP_001 | D6: 210824.82 | E6: 185755.83 | F6: 25068.994 | G6: 9124.9009 | H6: 690475.53 | I6: 452182.13 | J6: 238293.4 | K6: 11208.125 | L6: 4.3946872 | M6: 3.8292714 | N6: 1.3215386 | O6: 1.8975857 | P6: 362.3575 | Q6: 18412 | R6: 0.1225544 | S6: 766 | T6: 0.25606832 | U6: 0.04043359 | V6: 5.9746402 | W6: 62.772271 | X6: 5.514692 | Y6: 0 | Z6: 0 | AA6: 0 | AB6: 0 | AC6: 210554.56 | AD6: 0 | AE6: =IF(C7=C6,(D7-D6)/D6,"") -> 0.079315052 | AF6: =IF(C10=C6,(D10-D6)/D6,"") -> 0.035756742 | AG6: =(D:D-E:E)/D:D -> 0.11890912 | AH6: =G6/D6 -> 0.043281909 | AI6: =_xlfn.STDEV.P(D:D)/AVERAGE(D:D) -> 0.56010785 | AJ6: =(D7-D6)/D6 -> 0.079315052 | AK6: =(E7-E6)/E6 -> 0.10773453 | AL6: =AVERAGE(AJ:AJ) -> 0.021089248
A7: 2016 | B7: 2 | C7: CMP_001 | D7: 227546.41 | E7: 205768.15 | F7: 21778.258 | G7: 13732.339 | H7: 884178.69 | I7: 477055.24 | J7: 407123.45 | K7: 19154.113 | L7: 1.5387736 | M7: 3.3730161 | N7: 1.5531181 | O7: 1.1717705 | P7: 319.68994 | Q7: 43557 | R7: 0.26680751 | S7: 645 | T7: 0.45653457 | U7: 0.21844044 | V7: 3.9155696 | W7: 82.082006 | X7: 4.5947602 | Y7: 0 | Z7: 0 | AA7: 1 | AB7: 0 | AC7: 255190.8 | AD7: 1 | AE7: =IF(C8=C7,(D8-D7)/D7,"") -> -0.08515837 | AF7: =IF(C11=C7,(D11-D7)/D7,"") -> -0.014644901 | AG7: =(D:D-E:E)/D:D -> 0.095709083 | AH7: =G7/D7 -> 0.060349621 | AI7: =_xlfn.STDEV.P(D:D)/AVERAGE(D:D) -> 0.56010785 | AJ7: =(D8-D7)/D7 -> -0.08515837 | AK7: =(E8-E7)/E7 -> -0.088929822 | AL7: =AVERAGE(AJ:AJ) -> 0.021089248
A8: 2016 | B8: 3 | C8: CMP_001 | D8: 208168.92 | E8: 187469.22 | F8: 20699.702 | G8: 13229.864 | H8: 638699.49 | I8: 315474.11 | J8: 323225.38 | K8: 18616.404 | L8: 3.8630599 | M8: 4.093077 | N8: 2.0713754 | O8: 0.97601899 | P8: 137.18025 | Q8: 8994 | R8: -0.35359414 | S8: 607 | T8: 0.558102 | U8: 0.40383617 | V8: 1.4542457 | W8: 66.347885 | X8: 3.9750085 | Y8: 0 | Z8: 0 | AA8: 0 | AB8: 1 | AC8: 210735.51 | AD8: 0 | AE8: =IF(C9=C8,(D9-D8)/D8,"") -> 0.066413878 | AF8: =IF(C12=C8,(D12-D8)/D8,"") -> 0.12591394 | AG8: =(D:D-E:E)/D:D -> 0.09943704 | AH8: =G8/D8 -> 0.0635535 | AI8: =_xlfn.STDEV.P(D:D)/AVERAGE(D:D) -> 0.56010785 | AJ8: =(D9-D8)/D8 -> 0.066413878 | AK8: =(E9-E8)/E8 -> 0.11640768 | AL8: =AVERAGE(AJ:AJ) -> 0.021089248
A9: 2016 | B9: 4 | C9: CMP_001 | D9: 221994.23 | E9: 209292.08 | F9: 12702.149 | G9: -2508.4328 | H9: 679717.29 | I9: 325661.57 | J9: 354055.72 | K9: 784.96356 | L9: -0.39600973 | M9: -0.70848532 | N9: -0.3690406 | O9: 0.91980316 | P9: 58.809597 | Q9: 45215 | R9: -0.52472491 | S9: 766 | T9: 0.80313976 | U9: 0.47030063 | V9: 7.883962 | W9: 69.970611 | X9: 8.531455 | Y9: 0 | Z9: 0 | AA9: 0 | AB9: 0 | AC9: 215987.25 | AD9: 0 | AE9: =IF(C10=C9,(D10-D9)/D9,"") -> -0.01635627 | AF9: =IF(C13=C9,(D13-D9)/D9,"") -> 0.075689686 | AG9: =(D:D-E:E)/D:D -> 0.057218375 | AH9: =G9/D9 -> -0.01129954 | AI9: =_xlfn.STDEV.P(D:D)/AVERAGE(D:D) -> 0.56010785 | AJ9: =(D10-D9)/D9 -> -0.01635627 | AK9: =(E10-E9)/E9 -> -0.01753998 | AL9: =AVERAGE(AJ:AJ) -> 0.021089248
A10: 2017 | B10: 1 | C10: CMP_001 | D10: 218363.23 | E10: 205621.1 | F10: 12742.13 | G10: 4438.5146 | H10: 747304.29 | I10: 466168.73 | J10: 281135.56 | K10: 4668.5044 | L10: 2.3791493 | M10: 1.5787809 | N10: 0.59393672 | O10: 1.6581635 | P10: 471.45117 | Q10: 19343 | R10: -0.22652931 | S10: 337 | T10: 0.83771011 | U10: 0.67569012 | V10: 6.1465128 | W10: 65.226791 | X10: 6.3315838 | Y10: 0 | Z10: 0 | AA10: 0 | AB10: 1 | AC10: 209973.46 | AD10: 0 | AE10: =IF(C11=C10,(D11-D10)/D10,"") -> 0.026793789 | AF10: =IF(C14=C10,(D14-D10)/D10,"") -> -0.0096537939 | AG10: =(D:D-E:E)/D:D -> 0.058352911 | AH10: =G10/D10 -> 0.020326291 | AI10: =_xlfn.STDEV.P(D:D)/AVERAGE(D:D) -> 0.56010785 | AJ10: =(D11-D10)/D10 -> 0.026793789 | AK10: =(E11-E10)/E10 -> 0.0067262065 | AL10: =AVERAGE(AJ:AJ) -> 0.021089248
A11: 2017 | B11: 2 | C11: CMP_001 | D11: 224214.01 | E11: 207004.15 | F11: 17209.859 | G11: 9379.2521 | H11: 573481.75 | I11: 332701.5 | J11: 240780.25 | K11: 17079.169 | L11: 1.0772183 | M11: 3.8953577 | N11: 1.6354927 | O11: 1.3817641 | P11: 214.1639 | Q11: 13183 | R11: 0.7018569 | S11: 624 | T11: 0.16162871 | U11: 0.89855419 | V11: 5.2450034 | W11: 60.229926 | X11: 2.8117723 | Y11: 0 | Z11: 0 | AA11: 0 | AB11: 0 | AC11: 232307.43 | AD11: 0 | AE11: =IF(C12=C11,(D12-D11)/D11,"") -> 0.045341872 | AF11: =IF(C15=C11,(D15-D11)/D11,"") -> -0.030677536 | AG11: =(D:D-E:E)/D:D -> 0.076756393 | AH11: =G11/D11 -> 0.041831695 | AI11: =_xlfn.STDEV.P(D:D)/AVERAGE(D:D) -> 0.56010785 | AJ11: =(D12-D11)/D11 -> 0.045341872 | AK11: =(E12-E11)/E11 -> 0.015168817 | AL11: =AVERAGE(AJ:AJ) -> 0.021089248
A12: 2017 | B12: 3 | C12: CMP_001 | D12: 234380.29 | E12: 210144.16 | F12: 24236.134 | G12: 15872.094 | H12: 802602.14 | I12: 316947.29 | J12: 485654.85 | K12: 15753.089 | L12: 2.0563909 | M12: 3.268184 | N12: 1.9775793 | O12: 0.6526184 | P12: 331.82379 | Q12: 47214 | R12: 0.44187985 | S12: 639 | T12: 0.5683086 | U12: 0.093674768 | V12: 3.5740106 | W12: 66.630059 | X12: 3.9519171 | Y12: 1 | Z12: 0 | AA12: 0 | AB12: 0 | AC12: 241533.6 | AD12: 1 | AE12: =IF(C13=C12,(D13-D12)/D12,"") -> 0.018843775 | AF12: =IF(C16=C12,(D16-D12)/D12,"") -> -0.14177052 | AG12: =(D:D-E:E)/D:D -> 0.10340517 | AH12: =G12/D12 -> 0.067719405 | AI12: =_xlfn.STDEV.P(D:D)/AVERAGE(D:D) -> 0.56010785 | AJ12: =(D13-D12)/D12 -> 0.018843775 | AK12: =(E13-E12)/E12 -> -0.073176284 | AL12: =AVERAGE(AJ:AJ) -> 0.021089248
A13: 2017 | B13: 4 | C13: CMP_001 | D13: 238796.9 | E13: 194766.59 | F13: 44030.312 | G13: 36101.667 | H13: 822632.46 | I13: 339178.72 | J13: 483453.74 | K13: 31466.407 | L13: 5.3018561 | M13: 7.4674502 | N13: 4.3885537 | O13: 0.70157431 | P13: 105.01313 | Q13: 19589 | R13: 0.90785715 | S13: 372 | T13: 0.88349402 | U13: 0.74771877 | V13: 7.6715029 | W13: 68.268758 | X13: 6.4221197 | Y13: 0 | Z13: 1 | AA13: 0 | AB13: 0 | AC13: 271943.53 | AD13: 1 | AE13: =IF(C14=C13,(D14-D13)/D13,"") -> -0.094396972 | AF13: =IF(C17=C13,(D17-D13)/D13,"") -> -0.097510533 | AG13: =(D:D-E:E)/D:D -> 0.18438393 | AH13: =G13/D13 -> 0.15118147 | AI13: =_xlfn.STDEV.P(D:D)/AVERAGE(D:D) -> 0.56010785 | AJ13: =(D14-D13)/D13 -> -0.094396972 | AK13: =(E14-E13)/E13 -> -0.027258749 | AL13: =AVERAGE(AJ:AJ) -> 0.021089248
... A2001: 2024 | B2001: 4 | C2001: CMP_050 | D2001: 473669.77 | E2001: 377460.87 | F2001: 96208.891 | G2001: 77385.299 | H2001: 1827013.7 | I2001: 1121965.1 | J2001: 705048.54 | K2001: 73863.103 | L2001: 63.304244 | M2001: 10.975882 | N2001: 4.2356168 | O2001: 1.5913304 | P2001: 85.563228 | Q2001: 4766 | R2001: 0.35972615 | S2001: 625 | T2001: 0.36975917 | U2001: 0.14307703 | V2001: 6.267522 | W2001: 81.132413 | X2001: 5.9036204 | Y2001: 1 | Z2001: 0 | AA2001: 0 | AB2001: 0 | AC2001: 523157.78 | AD2001: 1 | AE2001: =IF(C2002=C2001,(D2002-D2001)/D2001,"") | AF2001: =IF(C2005=C2001,(D2005-D2001)/D2001,"") | AG2001: =(D:D-E:E)/D:D -> 0.20311385 | AH2001: =G2001/D2001 -> 0.16337395 | AI2001: =_xlfn.STDEV.P(D:D)/AVERAGE(D:D) -> 0.56010785 | AJ2001: =(D2002-D2001)/D2001 -> -0.53705662 | AK2001: =(E2002-E2001)/E2001 -> -1 | AL2001: =AVERAGE(AJ:AJ) -> 0.021089248
D2002: =D3*(1+0.02086) -> 219282.28
D2004: =D3-D2/D2 -> 214800.52 | E2004: =E3-E2/E2 -> 190522.23
D2005: =D4-D3/D3 -> 231900.99 | F2005: =average -> #NAME?
D2006: =D5-D4/D4 -> 213290.56
D2007: =D6-D5/D5 -> 210823.82
D2008: =D7-D6/D6 -> 227545.41 | AE2008: avg revenue growth | AI2008: =AVERAGE(Sheet1!AJ:AJ) -> 0.021089248
D2009: =D8-D7/D7 -> 208167.92
D2010: =D9-D8/D8 -> 221993.23

Sheet Sheet3
B3: Quarter | C3: Revenue | D3: Expenses | E3: Profit
B4: Current | C4: 464427.65 | D4: 422739.02 | E4: =(C4-D4) -> 41688.638 | G4: =Previous_Revenue*(1+0.02086) -> #NAME?
B5: Next Q1 | C5: =Sheet1!D3*(1+0.02086) -> 219282.28 | D5: =Sheet1!E3*(1+0.02039) -> 194408 | E5: =(C5-D5) -> 24874.284
B6: Next Q2 | C6: =Sheet1!D4*(1+0.02086) -> 236739.46 | D6: =Sheet1!E4*(1+0.02039) -> 189300.22 | E6: =(C6-D6) -> 47439.243
B7: Next Q3 | C7: =Sheet1!D5*(1+0.02086) -> 217740.82 | D7: =Sheet1!E5*(1+0.02039) -> 190191.41 | E7: =(C7-D7) -> 27549.415
B8: Next Q4 | C8: =Sheet1!D6*(1+0.02086) -> 215222.63 | D8: =Sheet1!E6*(1+0.02039) -> 189543.39 | E8: =(C8-D8) -> 25679.238
D16: S

Sheet calculations
A1: QOQ | B1: Column1 | C1: Column2 | D1: Column3 | E1: Column4 | F1: Column5 | G1: Column6 | H1: Column7 | I1: Column8 | J1: Column9 | K1: Column10 | L1: Column11 | M1: Column12 | AJ1: REVENUEGROWTH
AJ2: =(D3-D2)/D2 -> #DIV/0!
B3: MACRO CORRELATION (Risk Analysis) | AJ3: =(D4-D3)/D3 -> #DIV/0!
AJ4: =(D5-D4)/D4 -> #DIV/0!
AJ5: =(D6-D5)/D5 -> #DIV/0!
J6: Revenue vs Interest Rate | AJ6: =(D7-D6)/D6 -> #DIV/0!
B7: Revenue vs Inflation | AJ7: =(D8-D7)/D7 -> #DIV/0!
K8: =CORREL(Sheet1!D:D,Sheet1!X:X) -> -0.019223938 | AJ8: =(D9-D8)/D8 -> #DIV/0!
AJ9: =(D10-D9)/D9 -> #DIV/0!
B10: =CORREL(Sheet1!D:D,Sheet1!V:V) -> 0.017230185 | F10: Expenses vs Inflation | AJ10: =(D11-D10)/D10 -> #DIV/0!
AJ11: =(D12-D11)/D11 -> #DIV/0!
AJ12: =(D13-D12)/D12 -> #DIV/0!
AJ13: =(D14-D13)/D13 -> #DIV/0!
F14: =CORREL(Sheet1!E:E,Sheet1!V:V) -> 0.020790018 | AJ14: =(D15-D14)/D14 -> #DIV/0!
AJ15: =(D16-D15)/D15 -> #DIV/0!
AJ16: =(D17-D16)/D16 -> #DIV/0!
AJ17: =(D18-D17)/D17 -> #DIV/0!
AJ18: =(D19-D18)/D18 -> #DIV/0!
AJ19: =(D20-D19)/D19 -> #DIV/0!
AJ20: =(D21-D20)/D20 -> #DIV/0!
AJ21: =(D22-D21)/D21 -> #DIV/0!
AJ22: =(D23-D22)/D22 -> #DIV/0!
AJ23: =(D24-D23)/D23 -> #DIV/0!
AJ24: =(D25-D24)/D24 -> #DIV/0!
AJ25: =(D26-D25)/D25 -> #DIV/0!
AJ26: =(D27-D26)/D26 -> #DIV/0!
... AJ2001: =(D2002-D2001)/D2001 -> #DIV/0!

Sheet Sheet6
D2: BUDGET SCENERIO | E2: Column1 | F2: Column2 | G2: Column3 | H2: Column4 | I2: Column5
D3: Scenario | E3: Revenue Growth | F3: Forecast Revenue | G3: FORECAST EXPENSE | I3: Scenario
D4: Conservative | E4: 0.03 | F4: =214802*(1+0.03) -> 221246.06 | G4: =190523*(1+0.02039) -> 194407.76 | I4: Conservative
D5: Base | E5: 0.06 | F5: =214802*(1+0.06) -> 227690.12 | G5: =190523*(1+0.02039) -> 194407.76 | I5: Base
D6: Aggressive | E6: 0.09 | F6: =214802*(1+0.09) -> 234134.18 | G6: =190523*(1+0.02039) -> 194407.76 | I6: Aggressive
I8: =214802*(1+0.09) -> 234134.18
D10: CURRENT REVENUE | F10: 214802
B12: CONSERVATIVE | D12: =214802*(1+0.03) -> 221246.06
